geoakima/DataTrain.txt
geoakima/__init__.py
geoakima/geoakima.py
geoakima/src/akima.new.f
geoakima/src/tripack.f
geoakima-0.20.data/data/geoakima/DataTrain.txt
geoakima-0.20.dist-info/METADATA
geoakima-0.20.dist-info/WHEEL
geoakima-0.20.dist-info/top_level.txt
geoakima-0.20.dist-info/RECORD
