Metadata-Version: 2.1
Name: geoakima
Version: 0.20
Summary: This package allows to perform an interpolation with the Akima method specially adapted to fill the geographic data
Home-page: https://modelwiki.cerege.fr/
Author: G.Gassier and S.Meulé
Author-email: gassier@cerege.fr, meule@cerege.fr
License: ACM
Platform: UNKNOWN
Classifier: Programming Language :: Python
Classifier: Development Status :: 1 - Planning
Classifier: Natural Language :: French
Classifier: Operating System :: POSIX :: Linux
Classifier: Programming Language :: Python :: 3.5
Requires-Dist: numpy
Requires-Dist: shapely
Requires-Dist: matplotlib
Requires-Dist: scipy
Requires-Dist: descartes
Requires-Dist: pandas
Requires-Dist: geopandas
